earfcn/__init__.py
earfcn/convert.py
earfcn-0.0.3.dist-info/METADATA
earfcn-0.0.3.dist-info/WHEEL
earfcn-0.0.3.dist-info/entry_points.txt
earfcn-0.0.3.dist-info/top_level.txt
earfcn-0.0.3.dist-info/RECORD
